README.rst
setup.cfg
setup.py
minihmm/__init__.py
minihmm/estimators.py
minihmm/factors.py
minihmm/hmm.py
minihmm/represent.py
minihmm/training.py
minihmm/util.py
minihmm.egg-info/PKG-INFO
minihmm.egg-info/SOURCES.txt
minihmm.egg-info/dependency_links.txt
minihmm.egg-info/requires.txt
minihmm.egg-info/top_level.txt
minihmm/test/__init__.py
minihmm/test/common.py
minihmm/test/test_estimators.py
minihmm/test/test_factors.py
minihmm/test/test_hmm.py
minihmm/test/test_represent.py
minihmm/test/test_training.py
minihmm/test/test_util.py