Metadata-Version: 2.1
Name: minihmm
Version: 0.3.3
Summary: Lightweight extensible HMM engine, supporting univariate or multivariate, continuous or discrete emissions
Home-page: http://github.com/joshuagryphon/minihmm
Author: Joshua Griffin Dunn
Maintainer: Joshua Griffin Dunn
License: BSD 3-Clause
Keywords: HMM hidden Markov model machine learning modeling statistics
Platform: POSIX
Classifier: Development Status :: 4 - Beta
Classifier: Programming Language :: Python
Classifier: Programming Language :: Python :: 3.6
Classifier: Programming Language :: Python :: 3.9
Classifier: Topic :: Scientific/Engineering
Classifier: License :: OSI Approved :: BSD License
Classifier: Operating System :: POSIX
